hydra4/__init__.py
hydra4/_version.py
hydra4/hydra4.py
hydra4/structs.py
hydra4/calibrations/pandar_xt32.csv
hydra4/decoders/__init__.py
hydra4/decoders/base.py
hydra4/decoders/pandar_xt32.py
hydra4/msgs/__init__.py
hydra4/msgs/builtin_interfaces.py
hydra4/msgs/pandar_msgs.py
hydra4/msgs/std_msgs.py
hydra4-0.1.0.dist-info/METADATA
hydra4-0.1.0.dist-info/WHEEL
hydra4-0.1.0.dist-info/licenses/LICENSE.txt
hydra4-0.1.0.dist-info/RECORD
