Metadata-Version: 2.3
Name: hydra4
Version: 0.1.0
Summary: Decode Hesai Pandar Packets to NumPy arrays or PointCloud2 messages
Project-URL: Source, https://github.com/MapIV/hydra4
Project-URL: Tracker, https://github.com/MapIV/hydra4/issues
Project-URL: Release Notes, https://github.com/MapIV/hydra4/releases
Author-email: urasakikeisuke <keisuke.urasaki@map4.jp>
License:                                  Apache License
License-File: LICENSE.txt
Classifier: Development Status :: 3 - Alpha
Classifier: Framework :: Robot Framework :: Tool
Classifier: Intended Audience :: Developers
Classifier: License :: OSI Approved :: Apache Software License
Classifier: Operating System :: MacOS :: MacOS X
Classifier: Operating System :: Microsoft :: Windows
Classifier: Operating System :: POSIX
Classifier: Programming Language :: Python :: 3 :: Only
Classifier: Programming Language :: Python :: 3.8
Classifier: Programming Language :: Python :: 3.9
Classifier: Programming Language :: Python :: 3.10
Classifier: Programming Language :: Python :: 3.11
Classifier: Programming Language :: Python :: 3.12
Classifier: Programming Language :: Python :: Implementation :: CPython
Classifier: Topic :: Scientific/Engineering
Classifier: Topic :: Software Development :: Libraries
Classifier: Topic :: System :: Hardware :: Hardware Drivers
Classifier: Topic :: Utilities
Requires-Python: >=3.8
Requires-Dist: numpy>=1.21.0
Requires-Dist: pypcd4>=0.4.11
Provides-Extra: dev
Requires-Dist: mypy; extra == 'dev'
Requires-Dist: ruff; extra == 'dev'
Requires-Dist: setuptools-scm; extra == 'dev'
